setup.py
suanfa/__init__.py
suanfa/add_noise.py
suanfa.egg-info/PKG-INFO
suanfa.egg-info/SOURCES.txt
suanfa.egg-info/dependency_links.txt
suanfa.egg-info/top_level.txt