Metadata-Version: 2.1
Name: suanfa
Version: 0.1
Summary: hello,my friend
Home-page: https://github.com/
Author-email: 1711551881@qq.com
License: UNKNOWN
Platform: UNKNOWN
Classifier: Programming Language :: Python :: 3
Classifier: License :: OSI Approved :: MIT License
Classifier: Operating System :: OS Independent
